APIRetrys/ApiRetrys.py
APIRetrys/Logs.py
APIRetrys/MaxRetryExceptions.py
APIRetrys/__init__.py
APIRetrys-0.0.3.dist-info/LICENSE
APIRetrys-0.0.3.dist-info/METADATA
APIRetrys-0.0.3.dist-info/WHEEL
APIRetrys-0.0.3.dist-info/top_level.txt
APIRetrys-0.0.3.dist-info/RECORD
