Metadata-Version: 2.1
Name: APIRetrys
Version: 0.0.3
Summary: To handle API request retries due to timeouts
Author: Ryosoraa (Rio Dwi Saputra)
Author-email: <riodwi12174@gmail.com>
Keywords: python,request,retry,api,timeout,auto
Classifier: Development Status :: 1 - Planning
Classifier: Intended Audience :: Developers
Classifier: Programming Language :: Python
Classifier: Operating System :: Microsoft :: Windows
License-File: LICENSE
Requires-Dist: logging
